setup.py
gui_msg_client/__init__.py
gui_msg_client/client.py
gui_msg_client.egg-info/PKG-INFO
gui_msg_client.egg-info/SOURCES.txt
gui_msg_client.egg-info/dependency_links.txt
gui_msg_client.egg-info/requires.txt
gui_msg_client.egg-info/top_level.txt
gui_msg_client/client/__init__.py
gui_msg_client/client/add_contact.py
gui_msg_client/client/client_database.py
gui_msg_client/client/client_gui_designer.py
gui_msg_client/client/del_contact.py
gui_msg_client/client/main_window.py
gui_msg_client/client/start_dialog.py
gui_msg_client/client/transport.py
gui_msg_client/common/__init__.py
gui_msg_client/common/constants.py
gui_msg_client/common/decorators.py
gui_msg_client/common/descriptors_.py
gui_msg_client/common/exceptions.py
gui_msg_client/common/metaclasses.py
gui_msg_client/common/utils.py
gui_msg_client/log/__init__.py
gui_msg_client/log/client_log_config.py