Metadata-Version: 1.0
Name: gui-msg-client
Version: 0.5.4
Summary: Python GUI Messenger Client
Home-page: UNKNOWN
Author: Vlad Chekunov
Author-email: UNKNOWN
License: UNKNOWN
Platform: UNKNOWN
